<?xml version="1.0" encoding="utf-8"?><asx:abap xmlns:asx="http://www.sap.com/abapxml">
<asx:values>
<DD40L>
<DD40L>
<TYPENAME>NGCT_MSG_WITH_INDEX</TYPENAME>
<AS4LOCAL>N</AS4LOCAL>
<ACTFLAG></ACTFLAG>
<ROWTYPE>NGCS_MSG_WITH_INDEX</ROWTYPE>
<ROWKIND>S</ROWKIND>
<DATATYPE>STRU</DATATYPE>
<LENG>000000</LENG>
<DECIMALS>000000</DECIMALS>
<ACCESSMODE>T</ACCESSMODE>
<KEYDEF>D</KEYDEF>
<KEYKIND>N</KEYKIND>
<KEYFDCOUNT>0000</KEYFDCOUNT>
<GENERIC></GENERIC>
<TYPELEN>000452</TYPELEN>
<AS4USER>SAP</AS4USER>
<AS4DATE>2018-01-31</AS4DATE>
<AS4TIME>09:07:11</AS4TIME>
<TTYPKIND></TTYPKIND>
<RANGE_CTYP></RANGE_CTYP>
<REFTYPE></REFTYPE>
<OCCURS>00000</OCCURS>
<PROXYTYPE></PROXYTYPE>
<ALIAS></ALIAS>
<FURTHERSECKEY></FURTHERSECKEY>
<ABAP_LANGUAGE_VERSION></ABAP_LANGUAGE_VERSION>
</DD40L>
</DD40L>
<DD40T>
<DD40T>
<TYPENAME>NGCT_MSG_WITH_INDEX</TYPENAME>
<DDLANGUAGE>E</DDLANGUAGE>
<AS4LOCAL>N</AS4LOCAL>
<DDTEXT>NGC Message with Index</DDTEXT>
</DD40T>
</DD40T>
<DDTYPES>
<DDTYPES>
<TYPENAME>NGCT_MSG_WITH_INDEX</TYPENAME>
<STATE>N</STATE>
<TYPEKIND>TTYP</TYPEKIND>
</DDTYPES>
</DDTYPES>
<TADIR>
<TADIR>
<PGMID>R3TR</PGMID>
<OBJECT>TTYP</OBJECT>
<OBJ_NAME>NGCT_MSG_WITH_INDEX</OBJ_NAME>
<KORRNUM></KORRNUM>
<SRCSYSTEM>SAP</SRCSYSTEM>
<AUTHOR>SAP</AUTHOR>
<SRCDEP></SRCDEP>
<DEVCLASS>NGC_API_BASE</DEVCLASS>
<GENFLAG></GENFLAG>
<EDTFLAG></EDTFLAG>
<CPROJECT> S</CPROJECT>
<MASTERLANG>E</MASTERLANG>
<VERSID>0.0</VERSID>
<PAKNOCHECK></PAKNOCHECK>
<OBJSTABLTY></OBJSTABLTY>
<COMPONENT>S4CORE</COMPONENT>
<CRELEASE>103</CRELEASE>
<DELFLAG></DELFLAG>
<TRANSLTTXT></TRANSLTTXT>
<CREATED_ON>2017-10-12</CREATED_ON>
<CHECK_DATE>2017-10-12</CHECK_DATE>
<CHECK_CFG></CHECK_CFG>
</TADIR>
</TADIR>
</asx:values>
</asx:abap>