<?xml version="1.0" encoding="utf-8"?><asx:abap xmlns:asx="http://www.sap.com/abapxml">
<asx:values>
<DDDDLSRC>
<DDDDLSRC>
<DDLNAME>I_CLFNCHARACTERISTICFORKEYDATE</DDLNAME>
<AS4LOCAL>N</AS4LOCAL>
<AS4USER>SAP</AS4USER>
<AS4DATE>2020-06-15</AS4DATE>
<AS4TIME>18:36:31</AS4TIME>
<SOURCE>@ClientHandling.algorithm: #SESSION_VARIABLE
@AbapCatalog.sqlViewName: 'INGCCHR2'
@AbapCatalog.compiler.compareFilter: true
@AbapCatalog.preserveKey: true
@AccessControl.authorizationCheck: #CHECK
@AccessControl.privilegedAssociations: ['_CreatedByUser', '_LastChangedByUser']
@EndUserText.label: 'Classification Characteristic for Key Date'
@VDM.viewType: #COMPOSITE
@VDM.lifecycle.contract.type: #PUBLIC_LOCAL_API
@Metadata.ignorePropagatedAnnotations: true

@ObjectModel.representativeKey: 'CharcInternalID'
@ObjectModel.usageType.sizeCategory: #M
@ObjectModel.usageType.serviceQuality: #A
@ObjectModel.usageType.dataClass: #MASTER
/*+[hideWarning] { "IDS" : [ "KEY_CHECK" ] } */
define view I_ClfnCharacteristicForKeyDate
  with parameters
    @Consumption.hidden: true
    @Environment.systemField: #SYSTEM_DATE
    P_KeyDate : sydate
  as select from I_ClfnCharacteristic as Characteristic

      association [0..*] to I_ClfnCharcDescForKeyDate as _CharacteristicDesc
        on  _CharacteristicDesc.CharcInternalID  = $projection.CharcInternalID

      association [0..*] to I_ClfnCharcValueForKeyDate as _CharacteristicValue
        on _CharacteristicValue.CharcInternalID    = $projection.CharcInternalID


{
  key Characteristic.CharcInternalID,
      Characteristic.Characteristic,
      Characteristic.CharcStatus,
      Characteristic.CharcDataType,
      Characteristic.CharcLength,
      Characteristic.CharcDecimals,
      Characteristic.CharcTemplate,
      Characteristic.ValueIsCaseSensitive,
      Characteristic.CharcConversionRoutine,
      Characteristic.CharcGroup,
      Characteristic.EntryIsRequired,
      Characteristic.MultipleValuesAreAllowed,
      Characteristic.CharcValueUnit,
      Characteristic.Currency,
      Characteristic.CharcExponentValue,
      Characteristic.ValueIntervalIsAllowed,
      Characteristic.AdditionalValueIsAllowed,
      Characteristic.NegativeValueIsAllowed,
      @Semantics.businessDate.from: true
      Characteristic.ValidityStartDate,
      @Semantics.businessDate.to: true
      Characteristic.ValidityEndDate,
      Characteristic.ChangeNumber,
      Characteristic.DocumentInfoRecordDocType,
      Characteristic.DocumentInfoRecordDocNumber,
      Characteristic.DocumentInfoRecordDocVersion,
      Characteristic.DocumentInfoRecordDocPart,
      Characteristic.CharcMaintAuthGrp,
      Characteristic.CharcIsReadOnly,
      Characteristic.CharcIsHidden,
      Characteristic.CharcReferenceTable,
      Characteristic.CharcReferenceTableField,
      Characteristic.CharcCheckTable,
      Characteristic.CharcCheckFunctionModule,
      Characteristic.CharcExponentFormat,
      Characteristic.CharcEntryIsNotFormatCtrld,
      Characteristic.CharcTemplateIsDisplayed,
      Characteristic.CharcSelectedSet,
      Characteristic.Plant,
      Characteristic.CharcCatalogType,
      Characteristic.CreatedByUser,
      Characteristic.CreationDate,
      Characteristic.LastChangedByUser,
      Characteristic.LastChangeDate,
      Characteristic.CharcLastChangedDateTime,

      _CharacteristicDesc,
      _CharacteristicValue,
      _CharacteristicGroup,
      _CharacteristicStatus,
      _UnitOfMeasure,
      _Currency,
      _CreatedByUser,
      _LastChangedByUser
}
where Characteristic.ValidityStartDate   &lt;= $parameters.P_KeyDate
and   Characteristic.ValidityEndDate     &gt;= $parameters.P_KeyDate
and   Characteristic.IsDeleted = ''
/*+[internal] {
"BASEINFO":
{
"FROM":
[
"I_CLFNCHARACTERISTIC"
],
"ASSOCIATED":
[
"I_CLFNCHARCDESCFORKEYDATE",
"I_CLFNCHARCGROUP",
"I_CLFNCHARCSTATUS",
"I_CLFNCHARCVALUEFORKEYDATE",
"I_CURRENCY",
"I_UNITOFMEASURE",
"I_USER"
],
"BASE":
[
"I_CLFNCHARACTERISTIC"
],
"ANNO_REF":
[],
"VERSION":0
}
}*/</SOURCE>
<PARENTNAME></PARENTNAME>
<ACTFLAG></ACTFLAG>
<CHGFLAG></CHGFLAG>
<SOURCE_TYPE>V</SOURCE_TYPE>
<SOURCE_ORIGIN>0</SOURCE_ORIGIN>
<ABAP_LANGUAGE_VERSION></ABAP_LANGUAGE_VERSION>
</DDDDLSRC>
</DDDDLSRC>
<DDDDLSRC02BT>
<DDDDLSRC02BT>
<DDLNAME>I_CLFNCHARACTERISTICFORKEYDATE</DDLNAME>
<STRUCOBJN>I_CLFNCHARACTERISTICFORKEYDATE</STRUCOBJN>
<DDLANGUAGE>D</DDLANGUAGE>
<AS4LOCAL>N</AS4LOCAL>
<DDTEXT>Klassifizierungsmerkmal für Stichtag</DDTEXT>
</DDDDLSRC02BT>
<DDDDLSRC02BT>
<DDLNAME>I_CLFNCHARACTERISTICFORKEYDATE</DDLNAME>
<STRUCOBJN>I_CLFNCHARACTERISTICFORKEYDATE</STRUCOBJN>
<DDLANGUAGE>E</DDLANGUAGE>
<AS4LOCAL>N</AS4LOCAL>
<DDTEXT>Classification Characteristic for Key Date</DDTEXT>
</DDDDLSRC02BT>
<DDDDLSRC02BT>
<DDLNAME>I_CLFNCHARACTERISTICFORKEYDATE</DDLNAME>
<STRUCOBJN>I_CLFNCHARACTERISTICFORKEYDATE</STRUCOBJN>
<DDLANGUAGE>F</DDLANGUAGE>
<AS4LOCAL>N</AS4LOCAL>
<DDTEXT>Caractéristique de classification pour date clé</DDTEXT>
</DDDDLSRC02BT>
<DDDDLSRC02BT>
<DDLNAME>I_CLFNCHARACTERISTICFORKEYDATE</DDLNAME>
<STRUCOBJN>I_CLFNCHARACTERISTICFORKEYDATE</STRUCOBJN>
<DDLANGUAGE>N</DDLANGUAGE>
<AS4LOCAL>N</AS4LOCAL>
<DDTEXT>Classificatiekenmerk voor peildatum</DDTEXT>
</DDDDLSRC02BT>
<DDDDLSRC02BT>
<DDLNAME>I_CLFNCHARACTERISTICFORKEYDATE</DDLNAME>
<STRUCOBJN>I_CLFNCHARACTERISTICFORKEYDATE</STRUCOBJN>
<DDLANGUAGE>T</DDLANGUAGE>
<AS4LOCAL>N</AS4LOCAL>
<DDTEXT>Anahtar tarih için sınıflandırma karakteristiği</DDTEXT>
</DDDDLSRC02BT>
</DDDDLSRC02BT>
<DDDDLSRCT>
<DDDDLSRCT>
<DDLNAME>I_CLFNCHARACTERISTICFORKEYDATE</DDLNAME>
<DDLANGUAGE>E</DDLANGUAGE>
<AS4LOCAL>N</AS4LOCAL>
<DDTEXT>Classification Characteristic for Key Date</DDTEXT>
</DDDDLSRCT>
</DDDDLSRCT>
<DDFIELDANNO>
<DDFIELDANNO>
<STRUCOBJN>I_CLFNCHARACTERISTICFORKEYDATE</STRUCOBJN>
<LFIELDNAME>MANDT</LFIELDNAME>
<NAME>ABAPCATALOG</NAME>
<POSITION>1</POSITION>
<VALUE></VALUE>
</DDFIELDANNO>
<DDFIELDANNO>
<STRUCOBJN>I_CLFNCHARACTERISTICFORKEYDATE</STRUCOBJN>
<LFIELDNAME>MANDT</LFIELDNAME>
<NAME>ABAPCATALOG.INTERNAL</NAME>
<POSITION>2</POSITION>
<VALUE></VALUE>
</DDFIELDANNO>
<DDFIELDANNO>
<STRUCOBJN>I_CLFNCHARACTERISTICFORKEYDATE</STRUCOBJN>
<LFIELDNAME>MANDT</LFIELDNAME>
<NAME>ABAPCATALOG.INTERNAL.ISMANDT</NAME>
<POSITION>3</POSITION>
<VALUE></VALUE>
</DDFIELDANNO>
<DDFIELDANNO>
<STRUCOBJN>I_CLFNCHARACTERISTICFORKEYDATE</STRUCOBJN>
<LFIELDNAME>VALIDITYENDDATE</LFIELDNAME>
<NAME>SEMANTICS</NAME>
<POSITION>7</POSITION>
<VALUE></VALUE>
</DDFIELDANNO>
<DDFIELDANNO>
<STRUCOBJN>I_CLFNCHARACTERISTICFORKEYDATE</STRUCOBJN>
<LFIELDNAME>VALIDITYENDDATE</LFIELDNAME>
<NAME>SEMANTICS.BUSINESSDATE</NAME>
<POSITION>8</POSITION>
<VALUE></VALUE>
</DDFIELDANNO>
<DDFIELDANNO>
<STRUCOBJN>I_CLFNCHARACTERISTICFORKEYDATE</STRUCOBJN>
<LFIELDNAME>VALIDITYENDDATE</LFIELDNAME>
<NAME>SEMANTICS.BUSINESSDATE.TO</NAME>
<POSITION>9</POSITION>
<VALUE>true</VALUE>
</DDFIELDANNO>
<DDFIELDANNO>
<STRUCOBJN>I_CLFNCHARACTERISTICFORKEYDATE</STRUCOBJN>
<LFIELDNAME>VALIDITYSTARTDATE</LFIELDNAME>
<NAME>SEMANTICS</NAME>
<POSITION>4</POSITION>
<VALUE></VALUE>
</DDFIELDANNO>
<DDFIELDANNO>
<STRUCOBJN>I_CLFNCHARACTERISTICFORKEYDATE</STRUCOBJN>
<LFIELDNAME>VALIDITYSTARTDATE</LFIELDNAME>
<NAME>SEMANTICS.BUSINESSDATE</NAME>
<POSITION>5</POSITION>
<VALUE></VALUE>
</DDFIELDANNO>
<DDFIELDANNO>
<STRUCOBJN>I_CLFNCHARACTERISTICFORKEYDATE</STRUCOBJN>
<LFIELDNAME>VALIDITYSTARTDATE</LFIELDNAME>
<NAME>SEMANTICS.BUSINESSDATE.FROM</NAME>
<POSITION>6</POSITION>
<VALUE>true</VALUE>
</DDFIELDANNO>
</DDFIELDANNO>
<DDHEADANNO>
<DDHEADANNO>
<STRUCOBJN>I_CLFNCHARACTERISTICFORKEYDATE</STRUCOBJN>
<NAME>ABAPCATALOG</NAME>
<POSITION>1</POSITION>
<VALUE></VALUE>
</DDHEADANNO>
<DDHEADANNO>
<STRUCOBJN>I_CLFNCHARACTERISTICFORKEYDATE</STRUCOBJN>
<NAME>ABAPCATALOG.COMPILER</NAME>
<POSITION>3</POSITION>
<VALUE></VALUE>
</DDHEADANNO>
<DDHEADANNO>
<STRUCOBJN>I_CLFNCHARACTERISTICFORKEYDATE</STRUCOBJN>
<NAME>ABAPCATALOG.COMPILER.COMPAREFILTER</NAME>
<POSITION>4</POSITION>
<VALUE>true</VALUE>
</DDHEADANNO>
<DDHEADANNO>
<STRUCOBJN>I_CLFNCHARACTERISTICFORKEYDATE</STRUCOBJN>
<NAME>ABAPCATALOG.PRESERVEKEY</NAME>
<POSITION>5</POSITION>
<VALUE>true</VALUE>
</DDHEADANNO>
<DDHEADANNO>
<STRUCOBJN>I_CLFNCHARACTERISTICFORKEYDATE</STRUCOBJN>
<NAME>ABAPCATALOG.SQLVIEWNAME</NAME>
<POSITION>2</POSITION>
<VALUE>'INGCCHR2'</VALUE>
</DDHEADANNO>
<DDHEADANNO>
<STRUCOBJN>I_CLFNCHARACTERISTICFORKEYDATE</STRUCOBJN>
<NAME>ACCESSCONTROL</NAME>
<POSITION>8</POSITION>
<VALUE></VALUE>
</DDHEADANNO>
<DDHEADANNO>
<STRUCOBJN>I_CLFNCHARACTERISTICFORKEYDATE</STRUCOBJN>
<NAME>ACCESSCONTROL.AUTHORIZATIONCHECK</NAME>
<POSITION>9</POSITION>
<VALUE>#CHECK</VALUE>
</DDHEADANNO>
<DDHEADANNO>
<STRUCOBJN>I_CLFNCHARACTERISTICFORKEYDATE</STRUCOBJN>
<NAME>ACCESSCONTROL.PRIVILEGEDASSOCIATIONS$1$</NAME>
<POSITION>10</POSITION>
<VALUE>'_CreatedByUser'</VALUE>
</DDHEADANNO>
<DDHEADANNO>
<STRUCOBJN>I_CLFNCHARACTERISTICFORKEYDATE</STRUCOBJN>
<NAME>ACCESSCONTROL.PRIVILEGEDASSOCIATIONS$2$</NAME>
<POSITION>11</POSITION>
<VALUE>'_LastChangedByUser'</VALUE>
</DDHEADANNO>
<DDHEADANNO>
<STRUCOBJN>I_CLFNCHARACTERISTICFORKEYDATE</STRUCOBJN>
<NAME>CLIENTHANDLING</NAME>
<POSITION>6</POSITION>
<VALUE></VALUE>
</DDHEADANNO>
<DDHEADANNO>
<STRUCOBJN>I_CLFNCHARACTERISTICFORKEYDATE</STRUCOBJN>
<NAME>CLIENTHANDLING.ALGORITHM</NAME>
<POSITION>7</POSITION>
<VALUE>#SESSION_VARIABLE</VALUE>
</DDHEADANNO>
<DDHEADANNO>
<STRUCOBJN>I_CLFNCHARACTERISTICFORKEYDATE</STRUCOBJN>
<NAME>ENDUSERTEXT</NAME>
<POSITION>12</POSITION>
<VALUE></VALUE>
</DDHEADANNO>
<DDHEADANNO>
<STRUCOBJN>I_CLFNCHARACTERISTICFORKEYDATE</STRUCOBJN>
<NAME>ENDUSERTEXT.LABEL</NAME>
<POSITION>13</POSITION>
<VALUE>'Classification Characteristic for Key Date'</VALUE>
</DDHEADANNO>
<DDHEADANNO>
<STRUCOBJN>I_CLFNCHARACTERISTICFORKEYDATE</STRUCOBJN>
<NAME>METADATA</NAME>
<POSITION>19</POSITION>
<VALUE></VALUE>
</DDHEADANNO>
<DDHEADANNO>
<STRUCOBJN>I_CLFNCHARACTERISTICFORKEYDATE</STRUCOBJN>
<NAME>METADATA.IGNOREPROPAGATEDANNOTATIONS</NAME>
<POSITION>20</POSITION>
<VALUE>true</VALUE>
</DDHEADANNO>
<DDHEADANNO>
<STRUCOBJN>I_CLFNCHARACTERISTICFORKEYDATE</STRUCOBJN>
<NAME>OBJECTMODEL</NAME>
<POSITION>21</POSITION>
<VALUE></VALUE>
</DDHEADANNO>
<DDHEADANNO>
<STRUCOBJN>I_CLFNCHARACTERISTICFORKEYDATE</STRUCOBJN>
<NAME>OBJECTMODEL.REPRESENTATIVEKEY</NAME>
<POSITION>22</POSITION>
<VALUE>'CharcInternalID'</VALUE>
</DDHEADANNO>
<DDHEADANNO>
<STRUCOBJN>I_CLFNCHARACTERISTICFORKEYDATE</STRUCOBJN>
<NAME>OBJECTMODEL.USAGETYPE</NAME>
<POSITION>23</POSITION>
<VALUE></VALUE>
</DDHEADANNO>
<DDHEADANNO>
<STRUCOBJN>I_CLFNCHARACTERISTICFORKEYDATE</STRUCOBJN>
<NAME>OBJECTMODEL.USAGETYPE.DATACLASS</NAME>
<POSITION>26</POSITION>
<VALUE>#MASTER</VALUE>
</DDHEADANNO>
<DDHEADANNO>
<STRUCOBJN>I_CLFNCHARACTERISTICFORKEYDATE</STRUCOBJN>
<NAME>OBJECTMODEL.USAGETYPE.SERVICEQUALITY</NAME>
<POSITION>25</POSITION>
<VALUE>#A</VALUE>
</DDHEADANNO>
<DDHEADANNO>
<STRUCOBJN>I_CLFNCHARACTERISTICFORKEYDATE</STRUCOBJN>
<NAME>OBJECTMODEL.USAGETYPE.SIZECATEGORY</NAME>
<POSITION>24</POSITION>
<VALUE>#M</VALUE>
</DDHEADANNO>
<DDHEADANNO>
<STRUCOBJN>I_CLFNCHARACTERISTICFORKEYDATE</STRUCOBJN>
<NAME>VDM</NAME>
<POSITION>14</POSITION>
<VALUE></VALUE>
</DDHEADANNO>
<DDHEADANNO>
<STRUCOBJN>I_CLFNCHARACTERISTICFORKEYDATE</STRUCOBJN>
<NAME>VDM.LIFECYCLE</NAME>
<POSITION>16</POSITION>
<VALUE></VALUE>
</DDHEADANNO>
<DDHEADANNO>
<STRUCOBJN>I_CLFNCHARACTERISTICFORKEYDATE</STRUCOBJN>
<NAME>VDM.LIFECYCLE.CONTRACT</NAME>
<POSITION>17</POSITION>
<VALUE></VALUE>
</DDHEADANNO>
<DDHEADANNO>
<STRUCOBJN>I_CLFNCHARACTERISTICFORKEYDATE</STRUCOBJN>
<NAME>VDM.LIFECYCLE.CONTRACT.TYPE</NAME>
<POSITION>18</POSITION>
<VALUE>#PUBLIC_LOCAL_API</VALUE>
</DDHEADANNO>
<DDHEADANNO>
<STRUCOBJN>I_CLFNCHARACTERISTICFORKEYDATE</STRUCOBJN>
<NAME>VDM.VIEWTYPE</NAME>
<POSITION>15</POSITION>
<VALUE>#COMPOSITE</VALUE>
</DDHEADANNO>
</DDHEADANNO>
<DDPARAMETERANNO>
<DDPARAMETERANNO>
<STRUCOBJN>I_CLFNCHARACTERISTICFORKEYDATE</STRUCOBJN>
<PARAMETERNAME>P_KEYDATE</PARAMETERNAME>
<NAME>CONSUMPTION</NAME>
<PARPOS>1</PARPOS>
<VALUE></VALUE>
</DDPARAMETERANNO>
<DDPARAMETERANNO>
<STRUCOBJN>I_CLFNCHARACTERISTICFORKEYDATE</STRUCOBJN>
<PARAMETERNAME>P_KEYDATE</PARAMETERNAME>
<NAME>CONSUMPTION.HIDDEN</NAME>
<PARPOS>2</PARPOS>
<VALUE>true</VALUE>
</DDPARAMETERANNO>
<DDPARAMETERANNO>
<STRUCOBJN>I_CLFNCHARACTERISTICFORKEYDATE</STRUCOBJN>
<PARAMETERNAME>P_KEYDATE</PARAMETERNAME>
<NAME>ENVIRONMENT</NAME>
<PARPOS>3</PARPOS>
<VALUE></VALUE>
</DDPARAMETERANNO>
<DDPARAMETERANNO>
<STRUCOBJN>I_CLFNCHARACTERISTICFORKEYDATE</STRUCOBJN>
<PARAMETERNAME>P_KEYDATE</PARAMETERNAME>
<NAME>ENVIRONMENT.SYSTEMFIELD</NAME>
<PARPOS>4</PARPOS>
<VALUE>#SYSTEM_DATE</VALUE>
</DDPARAMETERANNO>
</DDPARAMETERANNO>
<TADIR>
<TADIR>
<PGMID>R3TR</PGMID>
<OBJECT>DDLS</OBJECT>
<OBJ_NAME>I_CLFNCHARACTERISTICFORKEYDATE</OBJ_NAME>
<KORRNUM></KORRNUM>
<SRCSYSTEM>SAP</SRCSYSTEM>
<AUTHOR>SAP</AUTHOR>
<SRCDEP></SRCDEP>
<DEVCLASS>NGC_CORE_VDM</DEVCLASS>
<GENFLAG></GENFLAG>
<EDTFLAG></EDTFLAG>
<CPROJECT> S</CPROJECT>
<MASTERLANG>E</MASTERLANG>
<VERSID>0.0</VERSID>
<PAKNOCHECK></PAKNOCHECK>
<OBJSTABLTY></OBJSTABLTY>
<COMPONENT>S4CORE</COMPONENT>
<CRELEASE>102</CRELEASE>
<DELFLAG></DELFLAG>
<TRANSLTTXT></TRANSLTTXT>
<CREATED_ON>2017-01-02</CREATED_ON>
<CHECK_DATE></CHECK_DATE>
<CHECK_CFG></CHECK_CFG>
</TADIR>
</TADIR>
</asx:values>
</asx:abap>